s2/UART2/dlatch/dlatch.v
module d_latch (
    input d,
    input en,
    input rstn,
    output reg q
);

    always @ (en or rstn or d) begin
        if (!rstn) // if rstn is 0 then enter the block
            begin
                q <= 0;
            end
        else
            begin
                if (en) begin 
                    q <= d;
                end
            end
    end
endmodule

s2/UART2/dlatch_tb.v
module tb_dlatch;

// We make the inputs registers? I am not too sure why.  
// the website says that I can drive them in an initial blcok but why can't I do this with wire?
reg d;
reg en; // en stands for enable.  programmers are absolutely terrible at naming
reg rstn;

reg prev_q; // This is for cheking that q did not change??

wire q;

d_latch     u0 (
            .d  (d),
            .en (en),
            .rstn (rstn),
            .q  (q)
            );


task checker (input d, en, rst, q);
    begin
        #1;
        if (!rstn) begin
            if (q!=0)
                $error("Q is not 0 during reset");      
        end else begin
            if (en) begin 
                if (q != d)
                    $error("Q is not following D when system is enabled (en = 1)");
            end else begin
                if (q != prev_q)
                    $error("Q is changing in between each cycle");
            end
        end
   end
endtask

// do some random testing to see what the output q gives us
task test_1();
    integer i;
    integer delay, delay2;
    begin
        for (i=0; i < 5; i = i+1) begin 
            //delay = $random;
            //delay2 = $random;
            #5 en <= ~en;  // do this at some random time later (delay and delay2 respectively)
            #1 d <= i;
            // then check the out values

            checker(d, en, rstn, q);
            prev_q <= q;    
        end
    end
endtask


task reset_release();
        #10 rstn <= 1; // after 10 time untis set the rstn signal to 1
endtask

initial begin // executes at clk=0.  Could also make this a fuinction instead. using 'function void init()'
    $dumpfile("dump.vcd");
    $dumpvars(0, tb_dlatch);
    d <= 0;
    en <= 0;
    rstn <= 0;

    reset_release();
    test_1();
    #5 $finish;
end


endmodule

s2/UART2/dump.vcd
$date
	Tue Aug 13 13:46:41 2024
$end
$version
	Icarus Verilog
$end
$timescale
	1s
$end
$scope module tb_dlatch $end
$var wire 1 ! q $end
$var reg 1 " d $end
$var reg 1 # en $end
$var reg 1 $ prev_q $end
$var reg 1 % rstn $end
$scope module u0 $end
$var wire 1 " d $end
$var wire 1 # en $end
$var wire 1 % rstn $end
$var reg 1 ! q $end
$upscope $end
$scope task checker $end
$var reg 1 & d $end
$var reg 1 ' en $end
$var reg 1 ( q $end
$var reg 1 ) rst $end
$upscope $end
$scope task reset_release $end
$upscope $end
$scope task test_1 $end
$var integer 32 * i [31:0] $end
$upscope $end
$upscope $end
$enddefinitions $end
$comment Show the parameter values. $end
$dumpall
$end
#0
$dumpvars
bx *
x)
x(
x'
x&
0%
x$
0#
0"
0!
$end
#10
1%
b0 *
#15
1#
#16
0(
1)
1'
0&
#17
0$
b1 *
#22
0#
#23
1"
0'
#24
b10 *
#29
1!
1#
#30
0!
0"
1(
1'
1&
#31
b11 *
#36
0#
#37
1"
0(
0'
0&
#38
b100 *
#43
1!
1#
#44
0!
0"
1(
1'
1&
#45
b101 *
