s2/UART2/UART.v
module UART (
    input rx,
    input clk,
    output reg [7:0] data_bus,
    output reg [7:0] probe
);

reg [7:0] the_byte = 8'b00000000; 
reg [2:0] byte_index = 3'b000;

reg [7:0] clock_count = 8'b00000000;


// imutable variables (possible states)
parameter idle = 3'b000; // listening
parameter start_bit = 3'b001; // start bit
parameter reading_bits = 3'b010; // reading byte
parameter stop_bit = 3'b100; // stop bit

// for the baud rate
parameter clks_per_bit = 40;
reg [2:0] reciever_state = 3'b000;

always @(posedge clk) begin
    case (reciever_state)
    idle:
        begin
            clock_count <= 0;
            byte_index <= 0;
            if (rx == 1'b0) begin
                probe <= 1;
                reciever_state <= start_bit;
            end
            else
                reciever_state <= idle;
        end
    start_bit:
        begin
            probe <= 0;
            if (clock_count == (clks_per_bit-1)/2) begin
                if (rx == 1'b0) begin// active low uar
                    clock_count <= 0;
                    reciever_state <= reading_bits;
                end
                else begin
                    clock_count <= 0;
                    reciever_state <= idle;
                end
            end
            else begin 
                clock_count <= clock_count + 1;
                reciever_state <= start_bit;
            end
        end
    reading_bits:
        begin
            if (clock_count <  clks_per_bit-1) begin
                clock_count <= clock_count + 1;
                reciever_state <= reading_bits; 
            end
            else begin
                clock_count <= 0; // why do you reset the clock count here?    
                the_byte[byte_index] <= rx;
                if (byte_index < 7) begin
                    byte_index <= byte_index + 1;
                    reciever_state <= reading_bits;
                end
                else begin
                    byte_index <= 3'b000;
                    reciever_state <= stop_bit;
                end
            end
        end
    stop_bit:
        if (clock_count < clks_per_bit-1)
            begin
                clock_count <= clock_count +1;
                reciever_state <= stop_bit;
            end
        else begin
            clock_count <= 0;
            reciever_state <= idle;
        end
    default:
        reciever_state <= idle;
    endcase
end
//assign data_bus = the_byte;
endmodule

s2/UART2/UART_tb.v
`timescale 10ns / 10ns;
module UART_tb;

reg  rx;
reg clk;
wire [7:0] probe;
wire [7:0] data_bus;


UART    u0 (
        .rx (rx),
        .clk (clk),
        .data_bus (data_bus),
        .probe (probe)
);

initial begin
    $dumpfile("uart_dump.vcd");
    $dumpvars(0, UART_tb);
    // sim the transmission

    clk <= 0; // init the clock
    rx <= 1; // idle
    #80 rx <= 0; // start bit
    $display("probe: %b", probe);
    #80 rx <= 0; // 0th bit
    #80 rx <= 1; // 1st bit
    #80 rx <= 0; // 2nd bit
    #80 rx <= 1; // 3rd bit
    #80 rx <= 0; // 4th bit
    #80 rx <= 1; // 5th bit
    #80 rx <= 0; // 6th bit
    #80 rx <= 1; // 7th bit
    #80 rx <= 1; // stop bit 
    #100;
    $display("Final data_bus value: %b", data_bus);
    $finish;
end

always #1 clk = ~clk;

endmodule

s2/UART2/uart_dump.vcd
$date
	Mon Aug 19 19:12:30 2024
$end
$version
	Icarus Verilog
$end
$timescale
	10ns
$end
$scope module UART_tb $end
$var wire 8 ! probe [7:0] $end
$var wire 8 " data_bus [7:0] $end
$var reg 1 # clk $end
$var reg 1 $ rx $end
$scope module u0 $end
$var wire 1 # clk $end
$var wire 1 $ rx $end
$var parameter 32 % clks_per_bit $end
$var parameter 3 & idle $end
$var parameter 3 ' reading_bits $end
$var parameter 3 ( start_bit $end
$var parameter 3 ) stop_bit $end
$var reg 3 * byte_index [2:0] $end
$var reg 8 + clock_count [7:0] $end
$var reg 8 , data_bus [7:0] $end
$var reg 8 - probe [7:0] $end
$var reg 3 . reciever_state [2:0] $end
$var reg 8 / the_byte [7:0] $end
$upscope $end
$upscope $end
$enddefinitions $end
$comment Show the parameter values. $end
$dumpall
b100 )
b1 (
b10 '
b0 &
b101000 %
$end
#0
$dumpvars
b0 /
b0 .
bx -
bx ,
b0 +
b0 *
1$
0#
bx "
bx !
$end
#1
1#
#2
0#
#3
1#
#4
0#
#5
1#
#6
0#
#7
1#
#8
0#
#9
1#
#10
0#
#11
1#
#12
0#
#13
1#
#14
0#
#15
1#
#16
0#
#17
1#
#18
0#
#19
1#
#20
0#
#21
1#
#22
0#
#23
1#
#24
0#
#25
1#
#26
0#
#27
1#
#28
0#
#29
1#
#30
0#
#31
1#
#32
0#
#33
1#
#34
0#
#35
1#
#36
0#
#37
1#
#38
0#
#39
1#
#40
0#
#41
1#
#42
0#
#43
1#
#44
0#
#45
1#
#46
0#
#47
1#
#48
0#
#49
1#
#50
0#
#51
1#
#52
0#
#53
1#
#54
0#
#55
1#
#56
0#
#57
1#
#58
0#
#59
1#
#60
0#
#61
1#
#62
0#
#63
1#
#64
0#
#65
1#
#66
0#
#67
1#
#68
0#
#69
1#
#70
0#
#71
1#
#72
0#
#73
1#
#74
0#
#75
1#
#76
0#
#77
1#
#78
0#
#79
1#
#80
0$
0#
#81
b1 .
b1 !
b1 -
1#
#82
0#
#83
b1 +
b0 !
b0 -
1#
#84
0#
#85
b10 +
1#
#86
0#
#87
b11 +
1#
#88
0#
#89
b100 +
1#
#90
0#
#91
b101 +
1#
#92
0#
#93
b110 +
1#
#94
0#
#95
b111 +
1#
#96
0#
#97
b1000 +
1#
#98
0#
#99
b1001 +
1#
#100
0#
#101
b1010 +
1#
#102
0#
#103
b1011 +
1#
#104
0#
#105
b1100 +
1#
#106
0#
#107
b1101 +
1#
#108
0#
#109
b1110 +
1#
#110
0#
#111
b1111 +
1#
#112
0#
#113
b10000 +
1#
#114
0#
#115
b10001 +
1#
#116
0#
#117
b10010 +
1#
#118
0#
#119
b10011 +
1#
#120
0#
#121
b10 .
b0 +
1#
#122
0#
#123
b1 +
1#
#124
0#
#125
b10 +
1#
#126
0#
#127
b11 +
1#
#128
0#
#129
b100 +
1#
#130
0#
#131
b101 +
1#
#132
0#
#133
b110 +
1#
#134
0#
#135
b111 +
1#
#136
0#
#137
b1000 +
1#
#138
0#
#139
b1001 +
1#
#140
0#
#141
b1010 +
1#
#142
0#
#143
b1011 +
1#
#144
0#
#145
b1100 +
1#
#146
0#
#147
b1101 +
1#
#148
0#
#149
b1110 +
1#
#150
0#
#151
b1111 +
1#
#152
0#
#153
b10000 +
1#
#154
0#
#155
b10001 +
1#
#156
0#
#157
b10010 +
1#
#158
0#
#159
b10011 +
1#
#160
0#
#161
b10100 +
1#
#162
0#
#163
b10101 +
1#
#164
0#
#165
b10110 +
1#
#166
0#
#167
b10111 +
1#
#168
0#
#169
b11000 +
1#
#170
0#
#171
b11001 +
1#
#172
0#
#173
b11010 +
1#
#174
0#
#175
b11011 +
1#
#176
0#
#177
b11100 +
1#
#178
0#
#179
b11101 +
1#
#180
0#
#181
b11110 +
1#
#182
0#
#183
b11111 +
1#
#184
0#
#185
b100000 +
1#
#186
0#
#187
b100001 +
1#
#188
0#
#189
b100010 +
1#
#190
0#
#191
b100011 +
1#
#192
0#
#193
b100100 +
1#
#194
0#
#195
b100101 +
1#
#196
0#
#197
b100110 +
1#
#198
0#
#199
b100111 +
1#
#200
0#
#201
b1 *
b0 +
1#
#202
0#
#203
b1 +
1#
#204
0#
#205
b10 +
1#
#206
0#
#207
b11 +
1#
#208
0#
#209
b100 +
1#
#210
0#
#211
b101 +
1#
#212
0#
#213
b110 +
1#
#214
0#
#215
b111 +
1#
#216
0#
#217
b1000 +
1#
#218
0#
#219
b1001 +
1#
#220
0#
#221
b1010 +
1#
#222
0#
#223
b1011 +
1#
#224
0#
#225
b1100 +
1#
#226
0#
#227
b1101 +
1#
#228
0#
#229
b1110 +
1#
#230
0#
#231
b1111 +
1#
#232
0#
#233
b10000 +
1#
#234
0#
#235
b10001 +
1#
#236
0#
#237
b10010 +
1#
#238
0#
#239
b10011 +
1#
#240
1$
0#
#241
b10100 +
1#
#242
0#
#243
b10101 +
1#
#244
0#
#245
b10110 +
1#
#246
0#
#247
b10111 +
1#
#248
0#
#249
b11000 +
1#
#250
0#
#251
b11001 +
1#
#252
0#
#253
b11010 +
1#
#254
0#
#255
b11011 +
1#
#256
0#
#257
b11100 +
1#
#258
0#
#259
b11101 +
1#
#260
0#
#261
b11110 +
1#
#262
0#
#263
b11111 +
1#
#264
0#
#265
b100000 +
1#
#266
0#
#267
b100001 +
1#
#268
0#
#269
b100010 +
1#
#270
0#
#271
b100011 +
1#
#272
0#
#273
b100100 +
1#
#274
0#
#275
b100101 +
1#
#276
0#
#277
b100110 +
1#
#278
0#
#279
b100111 +
1#
#280
0#
#281
b10 *
b10 /
b0 +
1#
#282
0#
#283
b1 +
1#
#284
0#
#285
b10 +
1#
#286
0#
#287
b11 +
1#
#288
0#
#289
b100 +
1#
#290
0#
#291
b101 +
1#
#292
0#
#293
b110 +
1#
#294
0#
#295
b111 +
1#
#296
0#
#297
b1000 +
1#
#298
0#
#299
b1001 +
1#
#300
0#
#301
b1010 +
1#
#302
0#
#303
b1011 +
1#
#304
0#
#305
b1100 +
1#
#306
0#
#307
b1101 +
1#
#308
0#
#309
b1110 +
1#
#310
0#
#311
b1111 +
1#
#312
0#
#313
b10000 +
1#
#314
0#
#315
b10001 +
1#
#316
0#
#317
b10010 +
1#
#318
0#
#319
b10011 +
1#
#320
0$
0#
#321
b10100 +
1#
#322
0#
#323
b10101 +
1#
#324
0#
#325
b10110 +
1#
#326
0#
#327
b10111 +
1#
#328
0#
#329
b11000 +
1#
#330
0#
#331
b11001 +
1#
#332
0#
#333
b11010 +
1#
#334
0#
#335
b11011 +
1#
#336
0#
#337
b11100 +
1#
#338
0#
#339
b11101 +
1#
#340
0#
#341
b11110 +
1#
#342
0#
#343
b11111 +
1#
#344
0#
#345
b100000 +
1#
#346
0#
#347
b100001 +
1#
#348
0#
#349
b100010 +
1#
#350
0#
#351
b100011 +
1#
#352
0#
#353
b100100 +
1#
#354
0#
#355
b100101 +
1#
#356
0#
#357
b100110 +
1#
#358
0#
#359
b100111 +
1#
#360
0#
#361
b11 *
b0 +
1#
#362
0#
#363
b1 +
1#
#364
0#
#365
b10 +
1#
#366
0#
#367
b11 +
1#
#368
0#
#369
b100 +
1#
#370
0#
#371
b101 +
1#
#372
0#
#373
b110 +
1#
#374
0#
#375
b111 +
1#
#376
0#
#377
b1000 +
1#
#378
0#
#379
b1001 +
1#
#380
0#
#381
b1010 +
1#
#382
0#
#383
b1011 +
1#
#384
0#
#385
b1100 +
1#
#386
0#
#387
b1101 +
1#
#388
0#
#389
b1110 +
1#
#390
0#
#391
b1111 +
1#
#392
0#
#393
b10000 +
1#
#394
0#
#395
b10001 +
1#
#396
0#
#397
b10010 +
1#
#398
0#
#399
b10011 +
1#
#400
1$
0#
#401
b10100 +
1#
#402
0#
#403
b10101 +
1#
#404
0#
#405
b10110 +
1#
#406
0#
#407
b10111 +
1#
#408
0#
#409
b11000 +
1#
#410
0#
#411
b11001 +
1#
#412
0#
#413
b11010 +
1#
#414
0#
#415
b11011 +
1#
#416
0#
#417
b11100 +
1#
#418
0#
#419
b11101 +
1#
#420
0#
#421
b11110 +
1#
#422
0#
#423
b11111 +
1#
#424
0#
#425
b100000 +
1#
#426
0#
#427
b100001 +
1#
#428
0#
#429
b100010 +
1#
#430
0#
#431
b100011 +
1#
#432
0#
#433
b100100 +
1#
#434
0#
#435
b100101 +
1#
#436
0#
#437
b100110 +
1#
#438
0#
#439
b100111 +
1#
#440
0#
#441
b100 *
b1010 /
b0 +
1#
#442
0#
#443
b1 +
1#
#444
0#
#445
b10 +
1#
#446
0#
#447
b11 +
1#
#448
0#
#449
b100 +
1#
#450
0#
#451
b101 +
1#
#452
0#
#453
b110 +
1#
#454
0#
#455
b111 +
1#
#456
0#
#457
b1000 +
1#
#458
0#
#459
b1001 +
1#
#460
0#
#461
b1010 +
1#
#462
0#
#463
b1011 +
1#
#464
0#
#465
b1100 +
1#
#466
0#
#467
b1101 +
1#
#468
0#
#469
b1110 +
1#
#470
0#
#471
b1111 +
1#
#472
0#
#473
b10000 +
1#
#474
0#
#475
b10001 +
1#
#476
0#
#477
b10010 +
1#
#478
0#
#479
b10011 +
1#
#480
0$
0#
#481
b10100 +
1#
#482
0#
#483
b10101 +
1#
#484
0#
#485
b10110 +
1#
#486
0#
#487
b10111 +
1#
#488
0#
#489
b11000 +
1#
#490
0#
#491
b11001 +
1#
#492
0#
#493
b11010 +
1#
#494
0#
#495
b11011 +
1#
#496
0#
#497
b11100 +
1#
#498
0#
#499
b11101 +
1#
#500
0#
#501
b11110 +
1#
#502
0#
#503
b11111 +
1#
#504
0#
#505
b100000 +
1#
#506
0#
#507
b100001 +
1#
#508
0#
#509
b100010 +
1#
#510
0#
#511
b100011 +
1#
#512
0#
#513
b100100 +
1#
#514
0#
#515
b100101 +
1#
#516
0#
#517
b100110 +
1#
#518
0#
#519
b100111 +
1#
#520
0#
#521
b101 *
b0 +
1#
#522
0#
#523
b1 +
1#
#524
0#
#525
b10 +
1#
#526
0#
#527
b11 +
1#
#528
0#
#529
b100 +
1#
#530
0#
#531
b101 +
1#
#532
0#
#533
b110 +
1#
#534
0#
#535
b111 +
1#
#536
0#
#537
b1000 +
1#
#538
0#
#539
b1001 +
1#
#540
0#
#541
b1010 +
1#
#542
0#
#543
b1011 +
1#
#544
0#
#545
b1100 +
1#
#546
0#
#547
b1101 +
1#
#548
0#
#549
b1110 +
1#
#550
0#
#551
b1111 +
1#
#552
0#
#553
b10000 +
1#
#554
0#
#555
b10001 +
1#
#556
0#
#557
b10010 +
1#
#558
0#
#559
b10011 +
1#
#560
1$
0#
#561
b10100 +
1#
#562
0#
#563
b10101 +
1#
#564
0#
#565
b10110 +
1#
#566
0#
#567
b10111 +
1#
#568
0#
#569
b11000 +
1#
#570
0#
#571
b11001 +
1#
#572
0#
#573
b11010 +
1#
#574
0#
#575
b11011 +
1#
#576
0#
#577
b11100 +
1#
#578
0#
#579
b11101 +
1#
#580
0#
#581
b11110 +
1#
#582
0#
#583
b11111 +
1#
#584
0#
#585
b100000 +
1#
#586
0#
#587
b100001 +
1#
#588
0#
#589
b100010 +
1#
#590
0#
#591
b100011 +
1#
#592
0#
#593
b100100 +
1#
#594
0#
#595
b100101 +
1#
#596
0#
#597
b100110 +
1#
#598
0#
#599
b100111 +
1#
#600
0#
#601
b110 *
b101010 /
b0 +
1#
#602
0#
#603
b1 +
1#
#604
0#
#605
b10 +
1#
#606
0#
#607
b11 +
1#
#608
0#
#609
b100 +
1#
#610
0#
#611
b101 +
1#
#612
0#
#613
b110 +
1#
#614
0#
#615
b111 +
1#
#616
0#
#617
b1000 +
1#
#618
0#
#619
b1001 +
1#
#620
0#
#621
b1010 +
1#
#622
0#
#623
b1011 +
1#
#624
0#
#625
b1100 +
1#
#626
0#
#627
b1101 +
1#
#628
0#
#629
b1110 +
1#
#630
0#
#631
b1111 +
1#
#632
0#
#633
b10000 +
1#
#634
0#
#635
b10001 +
1#
#636
0#
#637
b10010 +
1#
#638
0#
#639
b10011 +
1#
#640
0$
0#
#641
b10100 +
1#
#642
0#
#643
b10101 +
1#
#644
0#
#645
b10110 +
1#
#646
0#
#647
b10111 +
1#
#648
0#
#649
b11000 +
1#
#650
0#
#651
b11001 +
1#
#652
0#
#653
b11010 +
1#
#654
0#
#655
b11011 +
1#
#656
0#
#657
b11100 +
1#
#658
0#
#659
b11101 +
1#
#660
0#
#661
b11110 +
1#
#662
0#
#663
b11111 +
1#
#664
0#
#665
b100000 +
1#
#666
0#
#667
b100001 +
1#
#668
0#
#669
b100010 +
1#
#670
0#
#671
b100011 +
1#
#672
0#
#673
b100100 +
1#
#674
0#
#675
b100101 +
1#
#676
0#
#677
b100110 +
1#
#678
0#
#679
b100111 +
1#
#680
0#
#681
b111 *
b0 +
1#
#682
0#
#683
b1 +
1#
#684
0#
#685
b10 +
1#
#686
0#
#687
b11 +
1#
#688
0#
#689
b100 +
1#
#690
0#
#691
b101 +
1#
#692
0#
#693
b110 +
1#
#694
0#
#695
b111 +
1#
#696
0#
#697
b1000 +
1#
#698
0#
#699
b1001 +
1#
#700
0#
#701
b1010 +
1#
#702
0#
#703
b1011 +
1#
#704
0#
#705
b1100 +
1#
#706
0#
#707
b1101 +
1#
#708
0#
#709
b1110 +
1#
#710
0#
#711
b1111 +
1#
#712
0#
#713
b10000 +
1#
#714
0#
#715
b10001 +
1#
#716
0#
#717
b10010 +
1#
#718
0#
#719
b10011 +
1#
#720
1$
0#
#721
b10100 +
1#
#722
0#
#723
b10101 +
1#
#724
0#
#725
b10110 +
1#
#726
0#
#727
b10111 +
1#
#728
0#
#729
b11000 +
1#
#730
0#
#731
b11001 +
1#
#732
0#
#733
b11010 +
1#
#734
0#
#735
b11011 +
1#
#736
0#
#737
b11100 +
1#
#738
0#
#739
b11101 +
1#
#740
0#
#741
b11110 +
1#
#742
0#
#743
b11111 +
1#
#744
0#
#745
b100000 +
1#
#746
0#
#747
b100001 +
1#
#748
0#
#749
b100010 +
1#
#750
0#
#751
b100011 +
1#
#752
0#
#753
b100100 +
1#
#754
0#
#755
b100101 +
1#
#756
0#
#757
b100110 +
1#
#758
0#
#759
b100111 +
1#
#760
0#
#761
b100 .
b0 *
b10101010 /
b0 +
1#
#762
0#
#763
b1 +
1#
#764
0#
#765
b10 +
1#
#766
0#
#767
b11 +
1#
#768
0#
#769
b100 +
1#
#770
0#
#771
b101 +
1#
#772
0#
#773
b110 +
1#
#774
0#
#775
b111 +
1#
#776
0#
#777
b1000 +
1#
#778
0#
#779
b1001 +
1#
#780
0#
#781
b1010 +
1#
#782
0#
#783
b1011 +
1#
#784
0#
#785
b1100 +
1#
#786
0#
#787
b1101 +
1#
#788
0#
#789
b1110 +
1#
#790
0#
#791
b1111 +
1#
#792
0#
#793
b10000 +
1#
#794
0#
#795
b10001 +
1#
#796
0#
#797
b10010 +
1#
#798
0#
#799
b10011 +
1#
#800
0#
#801
b10100 +
1#
#802
0#
#803
b10101 +
1#
#804
0#
#805
b10110 +
1#
#806
0#
#807
b10111 +
1#
#808
0#
#809
b11000 +
1#
#810
0#
#811
b11001 +
1#
#812
0#
#813
b11010 +
1#
#814
0#
#815
b11011 +
1#
#816
0#
#817
b11100 +
1#
#818
0#
#819
b11101 +
1#
#820
0#
#821
b11110 +
1#
#822
0#
#823
b11111 +
1#
#824
0#
#825
b100000 +
1#
#826
0#
#827
b100001 +
1#
#828
0#
#829
b100010 +
1#
#830
0#
#831
b100011 +
1#
#832
0#
#833
b100100 +
1#
#834
0#
#835
b100101 +
1#
#836
0#
#837
b100110 +
1#
#838
0#
#839
b100111 +
1#
#840
0#
#841
b0 .
b0 +
1#
