s2/UART2/UARTt.v
module UARTtransmitter (
    input [7:0] In_byte,
    input data_bus_activate,
    input clk,
    output reg tx
);

reg [3:0] byte_index = 4'b0000;
reg [7:0] clock_count = 8'b00000000;
reg [9:0] uart_packet = 10'b0000000000;

// imutable variables (possible states)
parameter idle = 3'b000; // listening
parameter building_stream = 3'b001; // data bus has sent data
parameter sending_stream = 3'b010; // sending the bit stream

// for the baud rate
parameter clks_per_bit = 40;
reg [2:0] transmitter_state = 3'b000;

always @(posedge clk) begin
    case (transmitter_state)
    idle: // 000
        begin
            clock_count <= 0;
            byte_index <= 0;
            if (data_bus_activate == 1'b0) begin // active low transmitter
                transmitter_state <= building_stream;
            end
            else
                transmitter_state <= idle;
        end
    building_stream: // 001
        begin
            if (clock_count < clks_per_bit-1) begin
                clock_count <= clock_count + 1;
                transmitter_state <= building_stream;
            end
            else begin
                clock_count <= 0;
                if (byte_index == 0) begin
                    uart_packet[byte_index] = 1'b0; //start bit
                    byte_index <= byte_index + 1;
                end
                else if (byte_index == 9) begin
                    uart_packet[byte_index] = 1'b1; //stop bit
                    byte_index <= 0;
                    transmitter_state <= sending_stream;
                end
                else begin
                    uart_packet[byte_index] = In_byte[byte_index-1];
                    byte_index <= byte_index + 1;
                end
            end
        end
    sending_stream:  // 010
        begin
            if (clock_count <  clks_per_bit-1) begin
                clock_count <= clock_count + 1;
                transmitter_state <= sending_stream; 
            end
            else begin
                clock_count <= 0; // why do you reset the clock count here?    
                tx <= uart_packet[byte_index]; 
                if (byte_index < 9) begin
                    byte_index <= byte_index + 1;
                    transmitter_state <= sending_stream;
                end
                else begin
                    byte_index <= 3'b000;
                    data_bus_activate <= 1'b1
                    transmitter_state <= idle;
                end
            end
        end
    default:
        transmitter_state <= idle;
    endcase
end
endmodule

s2/UART2/UARTr.v
module UARTreceiver (
    input rx,
    input clk,
    output reg [7:0] data_bus
);

reg [7:0] the_byte = 8'b00000000; 
reg [2:0] byte_index = 3'b000;

reg [7:0] clock_count = 8'b00000000;


// imutable variables (possible states)
parameter idle = 3'b000; // listening
parameter start_bit = 3'b001; // start bit
parameter reading_bits = 3'b010; // reading byte
parameter stop_bit = 3'b100; // stop bit

// for the baud rate
parameter clks_per_bit = 40;
reg [2:0] reciever_state = 3'b000;

always @(posedge clk) begin
    case (reciever_state)
    idle:
        begin
            clock_count <= 0;
            byte_index <= 0;
            if (rx == 1'b0) begin
                reciever_state <= start_bit;
            end
            else
                reciever_state <= idle;
        end
    start_bit:
        begin
            if (clock_count == (clks_per_bit-1)/2) begin
                if (rx == 1'b0) begin// active low uar
                    clock_count <= 0;
                    reciever_state <= reading_bits;
                end
                else begin
                    clock_count <= 0;
                    reciever_state <= idle;
                end
            end
            else begin 
                clock_count <= clock_count + 1;
                reciever_state <= start_bit;
            end
        end
    reading_bits:
        begin
            if (clock_count <  clks_per_bit-1) begin
                clock_count <= clock_count + 1;
                reciever_state <= reading_bits; 
            end
            else begin
                clock_count <= 0; // why do you reset the clock count here?    
                the_byte[byte_index] <= rx;
                if (byte_index < 7) begin
                    byte_index <= byte_index + 1;
                    reciever_state <= reading_bits;
                end
                else begin
                    byte_index <= 3'b000;
                    reciever_state <= stop_bit;
                end
            end
        end
    stop_bit:
        if (clock_count < clks_per_bit-1)begin
            clock_count <= clock_count +1; 
            reciever_state <= stop_bit;
        end
        else begin
            data_bus <= the_byte;
            clock_count <= 0;
            reciever_state <= idle;
        end
    default:
        reciever_state <= idle;
    endcase
end
endmodule

s2/UART2/UART_tb.v
`timescale 10ns / 10ns;
module UART_tb;


// Global values
reg clk;

// receiver intialised values
reg  rx;
wire [7:0] data_bus;

// transmitter initialised values
reg [7:0] In_byte;
reg data_bus_activate;
wire tx;

// for the for loop
integer i;

UARTreceiver    receiver (
        .rx (rx),
        .clk (clk),
        .data_bus (data_bus)
);

UARTtransmitter    transmitter (
        .In_byte (In_byte),
        .data_bus_activate (data_bus_activate),
        .clk (clk),
        .tx (tx)
);


initial begin
    $dumpfile("uart_dump.vcd");
    $dumpvars(0, UART_tb);
    // sim the transmission

    clk <= 0; // init the clock
    rx <= 1; // idle receiver
    data_bus_activate <= 1'b1; // idle transmitter
    #80 In_byte <= 8'b01010101; // preparing the message. The test bench is acting as the data bus now
    #80 data_bus_activate <= 1'b0;
    for (i = 0; i < 10; i = i+1) begin
        #80 rx <= tx;
    end
    #100;
    $display("Final data_bus value: %b", data_bus);
    $finish;
end

always #1 clk = ~clk;

endmodule



    // #80 rx <= 0; // start bit
    // #80 rx <= 0; // 0th bit LSB
    // #80 rx <= 1; // 1st bit
    // #80 rx <= 0; // 2nd bit
    // #80 rx <= 1; // 3rd bit
    // #80 rx <= 0; // 4th bit
    // #80 rx <= 1; // 5th bit
    // #80 rx <= 0; // 6th bit
    // #80 rx <= 1; // 7th bit MSB
    // #80 rx <= 1; // stop bit

s2/UART2/uart_dump.vcd
$date
	Tue Aug 20 18:31:06 2024
$end
$version
	Icarus Verilog
$end
$timescale
	10ns
$end
$scope module UART_tb $end
$var wire 1 ! tx $end
$var wire 8 " data_bus [7:0] $end
$var reg 8 # In_byte [7:0] $end
$var reg 1 $ clk $end
$var reg 1 % data_bus_activate $end
$var reg 1 & rx $end
$var integer 32 ' i [31:0] $end
$scope module receiver $end
$var wire 1 $ clk $end
$var wire 1 & rx $end
$var parameter 32 ( clks_per_bit $end
$var parameter 3 ) idle $end
$var parameter 3 * reading_bits $end
$var parameter 3 + start_bit $end
$var parameter 3 , stop_bit $end
$var reg 3 - byte_index [2:0] $end
$var reg 8 . clock_count [7:0] $end
$var reg 8 / data_bus [7:0] $end
$var reg 3 0 reciever_state [2:0] $end
$var reg 8 1 the_byte [7:0] $end
$upscope $end
$scope module transmitter $end
$var wire 8 2 In_byte [7:0] $end
$var wire 1 $ clk $end
$var wire 1 % data_bus_activate $end
$var parameter 3 3 building_stream $end
$var parameter 32 4 clks_per_bit $end
$var parameter 3 5 idle $end
$var parameter 3 6 sending_stream $end
$var reg 4 7 byte_index [3:0] $end
$var reg 8 8 clock_count [7:0] $end
$var reg 3 9 transmitter_state [2:0] $end
$var reg 1 ! tx $end
$var reg 10 : uart_packet [9:0] $end
$upscope $end
$upscope $end
$enddefinitions $end
$comment Show the parameter values. $end
$dumpall
b10 6
b0 5
b101000 4
b1 3
b100 ,
b1 +
b10 *
b0 )
b101000 (
$end
#0
$dumpvars
b0 :
b0 9
b0 8
b0 7
bx 2
b0 1
b0 0
bx /
b0 .
b0 -
bx '
1&
1%
0$
bx #
bx "
x!
$end
#1
1$
#2
0$
#3
1$
#4
0$
#5
1$
#6
0$
#7
1$
#8
0$
#9
1$
#10
0$
#11
1$
#12
0$
#13
1$
#14
0$
#15
1$
#16
0$
#17
1$
#18
0$
#19
1$
#20
0$
#21
1$
#22
0$
#23
1$
#24
0$
#25
1$
#26
0$
#27
1$
#28
0$
#29
1$
#30
0$
#31
1$
#32
0$
#33
1$
#34
0$
#35
1$
#36
0$
#37
1$
#38
0$
#39
1$
#40
0$
#41
1$
#42
0$
#43
1$
#44
0$
#45
1$
#46
0$
#47
1$
#48
0$
#49
1$
#50
0$
#51
1$
#52
0$
#53
1$
#54
0$
#55
1$
#56
0$
#57
1$
#58
0$
#59
1$
#60
0$
#61
1$
#62
0$
#63
1$
#64
0$
#65
1$
#66
0$
#67
1$
#68
0$
#69
1$
#70
0$
#71
1$
#72
0$
#73
1$
#74
0$
#75
1$
#76
0$
#77
1$
#78
0$
#79
1$
#80
b1010101 #
b1010101 2
0$
#81
1$
#82
0$
#83
1$
#84
0$
#85
1$
#86
0$
#87
1$
#88
0$
#89
1$
#90
0$
#91
1$
#92
0$
#93
1$
#94
0$
#95
1$
#96
0$
#97
1$
#98
0$
#99
1$
#100
0$
#101
1$
#102
0$
#103
1$
#104
0$
#105
1$
#106
0$
#107
1$
#108
0$
#109
1$
#110
0$
#111
1$
#112
0$
#113
1$
#114
0$
#115
1$
#116
0$
#117
1$
#118
0$
#119
1$
#120
0$
#121
1$
#122
0$
#123
1$
#124
0$
#125
1$
#126
0$
#127
1$
#128
0$
#129
1$
#130
0$
#131
1$
#132
0$
#133
1$
#134
0$
#135
1$
#136
0$
#137
1$
#138
0$
#139
1$
#140
0$
#141
1$
#142
0$
#143
1$
#144
0$
#145
1$
#146
0$
#147
1$
#148
0$
#149
1$
#150
0$
#151
1$
#152
0$
#153
1$
#154
0$
#155
1$
#156
0$
#157
1$
#158
0$
#159
1$
#160
0%
0$
b0 '
#161
b1 9
1$
#162
0$
#163
b1 8
1$
#164
0$
#165
b10 8
1$
#166
0$
#167
b11 8
1$
#168
0$
#169
b100 8
1$
#170
0$
#171
b101 8
1$
#172
0$
#173
b110 8
1$
#174
0$
#175
b111 8
1$
#176
0$
#177
b1000 8
1$
#178
0$
#179
b1001 8
1$
#180
0$
#181
b1010 8
1$
#182
0$
#183
b1011 8
1$
#184
0$
#185
b1100 8
1$
#186
0$
#187
b1101 8
1$
#188
0$
#189
b1110 8
1$
#190
0$
#191
b1111 8
1$
#192
0$
#193
b10000 8
1$
#194
0$
#195
b10001 8
1$
#196
0$
#197
b10010 8
1$
#198
0$
#199
b10011 8
1$
#200
0$
#201
b10100 8
1$
#202
0$
#203
b10101 8
1$
#204
0$
#205
b10110 8
1$
#206
0$
#207
b10111 8
1$
#208
0$
#209
b11000 8
1$
#210
0$
#211
b11001 8
1$
#212
0$
#213
b11010 8
1$
#214
0$
#215
b11011 8
1$
#216
0$
#217
b11100 8
1$
#218
0$
#219
b11101 8
1$
#220
0$
#221
b11110 8
1$
#222
0$
#223
b11111 8
1$
#224
0$
#225
b100000 8
1$
#226
0$
#227
b100001 8
1$
#228
0$
#229
b100010 8
1$
#230
0$
#231
b100011 8
1$
#232
0$
#233
b100100 8
1$
#234
0$
#235
b100101 8
1$
#236
0$
#237
b100110 8
1$
#238
0$
#239
b100111 8
1$
#240
0$
#241
b1 7
b0 8
1$
#242
0$
#243
b1 8
1$
#244
0$
#245
b10 8
1$
#246
0$
#247
b11 8
1$
#248
0$
#249
b100 8
1$
#250
0$
#251
b101 8
1$
#252
0$
#253
b110 8
1$
#254
0$
#255
b111 8
1$
#256
0$
#257
b1000 8
1$
#258
0$
#259
b1001 8
1$
#260
0$
#261
b1010 8
1$
#262
0$
#263
b1011 8
1$
#264
0$
#265
b1100 8
1$
#266
0$
#267
b1101 8
1$
#268
0$
#269
b1110 8
1$
#270
0$
#271
b1111 8
1$
#272
0$
#273
b10000 8
1$
#274
0$
#275
b10001 8
1$
#276
0$
#277
b10010 8
1$
#278
0$
#279
b10011 8
1$
#280
0$
#281
b10100 8
1$
#282
0$
#283
b10101 8
1$
#284
0$
#285
b10110 8
1$
#286
0$
#287
b10111 8
1$
#288
0$
#289
b11000 8
1$
#290
0$
#291
b11001 8
1$
#292
0$
#293
b11010 8
1$
#294
0$
#295
b11011 8
1$
#296
0$
#297
b11100 8
1$
#298
0$
#299
b11101 8
1$
#300
0$
#301
b11110 8
1$
#302
0$
#303
b11111 8
1$
#304
0$
#305
b100000 8
1$
#306
0$
#307
b100001 8
1$
#308
0$
#309
b100010 8
1$
#310
0$
#311
b100011 8
1$
#312
0$
#313
b100100 8
1$
#314
0$
#315
b100101 8
1$
#316
0$
#317
b100110 8
1$
#318
0$
#319
b100111 8
1$
#320
0$
#321
b10 7
b0 8
b10 :
1$
#322
0$
#323
b1 8
1$
#324
0$
#325
b10 8
1$
#326
0$
#327
b11 8
1$
#328
0$
#329
b100 8
1$
#330
0$
#331
b101 8
1$
#332
0$
#333
b110 8
1$
#334
0$
#335
b111 8
1$
#336
0$
#337
b1000 8
1$
#338
0$
#339
b1001 8
1$
#340
0$
#341
b1010 8
1$
#342
0$
#343
b1011 8
1$
#344
0$
#345
b1100 8
1$
#346
0$
#347
b1101 8
1$
#348
0$
#349
b1110 8
1$
#350
0$
#351
b1111 8
1$
#352
0$
#353
b10000 8
1$
#354
0$
#355
b10001 8
1$
#356
0$
#357
b10010 8
1$
#358
0$
#359
b10011 8
1$
#360
0$
#361
b10100 8
1$
#362
0$
#363
b10101 8
1$
#364
0$
#365
b10110 8
1$
#366
0$
#367
b10111 8
1$
#368
0$
#369
b11000 8
1$
#370
0$
#371
b11001 8
1$
#372
0$
#373
b11010 8
1$
#374
0$
#375
b11011 8
1$
#376
0$
#377
b11100 8
1$
#378
0$
#379
b11101 8
1$
#380
0$
#381
b11110 8
1$
#382
0$
#383
b11111 8
1$
#384
0$
#385
b100000 8
1$
#386
0$
#387
b100001 8
1$
#388
0$
#389
b100010 8
1$
#390
0$
#391
b100011 8
1$
#392
0$
#393
b100100 8
1$
#394
0$
#395
b100101 8
1$
#396
0$
#397
b100110 8
1$
#398
0$
#399
b100111 8
1$
#400
0$
#401
b11 7
b0 8
1$
#402
0$
#403
b1 8
1$
#404
0$
#405
b10 8
1$
#406
0$
#407
b11 8
1$
#408
0$
#409
b100 8
1$
#410
0$
#411
b101 8
1$
#412
0$
#413
b110 8
1$
#414
0$
#415
b111 8
1$
#416
0$
#417
b1000 8
1$
#418
0$
#419
b1001 8
1$
#420
0$
#421
b1010 8
1$
#422
0$
#423
b1011 8
1$
#424
0$
#425
b1100 8
1$
#426
0$
#427
b1101 8
1$
#428
0$
#429
b1110 8
1$
#430
0$
#431
b1111 8
1$
#432
0$
#433
b10000 8
1$
#434
0$
#435
b10001 8
1$
#436
0$
#437
b10010 8
1$
#438
0$
#439
b10011 8
1$
#440
0$
#441
b10100 8
1$
#442
0$
#443
b10101 8
1$
#444
0$
#445
b10110 8
1$
#446
0$
#447
b10111 8
1$
#448
0$
#449
b11000 8
1$
#450
0$
#451
b11001 8
1$
#452
0$
#453
b11010 8
1$
#454
0$
#455
b11011 8
1$
#456
0$
#457
b11100 8
1$
#458
0$
#459
b11101 8
1$
#460
0$
#461
b11110 8
1$
#462
0$
#463
b11111 8
1$
#464
0$
#465
b100000 8
1$
#466
0$
#467
b100001 8
1$
#468
0$
#469
b100010 8
1$
#470
0$
#471
b100011 8
1$
#472
0$
#473
b100100 8
1$
#474
0$
#475
b100101 8
1$
#476
0$
#477
b100110 8
1$
#478
0$
#479
b100111 8
1$
#480
0$
#481
b100 7
b0 8
b1010 :
1$
#482
0$
#483
b1 8
1$
#484
0$
#485
b10 8
1$
#486
0$
#487
b11 8
1$
#488
0$
#489
b100 8
1$
#490
0$
#491
b101 8
1$
#492
0$
#493
b110 8
1$
#494
0$
#495
b111 8
1$
#496
0$
#497
b1000 8
1$
#498
0$
#499
b1001 8
1$
#500
0$
#501
b1010 8
1$
#502
0$
#503
b1011 8
1$
#504
0$
#505
b1100 8
1$
#506
0$
#507
b1101 8
1$
#508
0$
#509
b1110 8
1$
#510
0$
#511
b1111 8
1$
#512
0$
#513
b10000 8
1$
#514
0$
#515
b10001 8
1$
#516
0$
#517
b10010 8
1$
#518
0$
#519
b10011 8
1$
#520
0$
#521
b10100 8
1$
#522
0$
#523
b10101 8
1$
#524
0$
#525
b10110 8
1$
#526
0$
#527
b10111 8
1$
#528
0$
#529
b11000 8
1$
#530
0$
#531
b11001 8
1$
#532
0$
#533
b11010 8
1$
#534
0$
#535
b11011 8
1$
#536
0$
#537
b11100 8
1$
#538
0$
#539
b11101 8
1$
#540
0$
#541
b11110 8
1$
#542
0$
#543
b11111 8
1$
#544
0$
#545
b100000 8
1$
#546
0$
#547
b100001 8
1$
#548
0$
#549
b100010 8
1$
#550
0$
#551
b100011 8
1$
#552
0$
#553
b100100 8
1$
#554
0$
#555
b100101 8
1$
#556
0$
#557
b100110 8
1$
#558
0$
#559
b100111 8
1$
#560
x&
0$
b1 '
#561
b101 7
b0 8
1$
#562
0$
#563
b1 8
1$
#564
0$
#565
b10 8
1$
#566
0$
#567
b11 8
1$
#568
0$
#569
b100 8
1$
#570
0$
#571
b101 8
1$
#572
0$
#573
b110 8
1$
#574
0$
#575
b111 8
1$
#576
0$
#577
b1000 8
1$
#578
0$
#579
b1001 8
1$
#580
0$
#581
b1010 8
1$
#582
0$
#583
b1011 8
1$
#584
0$
#585
b1100 8
1$
#586
0$
#587
b1101 8
1$
#588
0$
#589
b1110 8
1$
#590
0$
#591
b1111 8
1$
#592
0$
#593
b10000 8
1$
#594
0$
#595
b10001 8
1$
#596
0$
#597
b10010 8
1$
#598
0$
#599
b10011 8
1$
#600
0$
#601
b10100 8
1$
#602
0$
#603
b10101 8
1$
#604
0$
#605
b10110 8
1$
#606
0$
#607
b10111 8
1$
#608
0$
#609
b11000 8
1$
#610
0$
#611
b11001 8
1$
#612
0$
#613
b11010 8
1$
#614
0$
#615
b11011 8
1$
#616
0$
#617
b11100 8
1$
#618
0$
#619
b11101 8
1$
#620
0$
#621
b11110 8
1$
#622
0$
#623
b11111 8
1$
#624
0$
#625
b100000 8
1$
#626
0$
#627
b100001 8
1$
#628
0$
#629
b100010 8
1$
#630
0$
#631
b100011 8
1$
#632
0$
#633
b100100 8
1$
#634
0$
#635
b100101 8
1$
#636
0$
#637
b100110 8
1$
#638
0$
#639
b100111 8
1$
#640
0$
#641
b110 7
b0 8
b101010 :
1$
#642
0$
#643
b1 8
1$
#644
0$
#645
b10 8
1$
#646
0$
#647
b11 8
1$
#648
0$
#649
b100 8
1$
#650
0$
#651
b101 8
1$
#652
0$
#653
b110 8
1$
#654
0$
#655
b111 8
1$
#656
0$
#657
b1000 8
1$
#658
0$
#659
b1001 8
1$
#660
0$
#661
b1010 8
1$
#662
0$
#663
b1011 8
1$
#664
0$
#665
b1100 8
1$
#666
0$
#667
b1101 8
1$
#668
0$
#669
b1110 8
1$
#670
0$
#671
b1111 8
1$
#672
0$
#673
b10000 8
1$
#674
0$
#675
b10001 8
1$
#676
0$
#677
b10010 8
1$
#678
0$
#679
b10011 8
1$
#680
0$
#681
b10100 8
1$
#682
0$
#683
b10101 8
1$
#684
0$
#685
b10110 8
1$
#686
0$
#687
b10111 8
1$
#688
0$
#689
b11000 8
1$
#690
0$
#691
b11001 8
1$
#692
0$
#693
b11010 8
1$
#694
0$
#695
b11011 8
1$
#696
0$
#697
b11100 8
1$
#698
0$
#699
b11101 8
1$
#700
0$
#701
b11110 8
1$
#702
0$
#703
b11111 8
1$
#704
0$
#705
b100000 8
1$
#706
0$
#707
b100001 8
1$
#708
0$
#709
b100010 8
1$
#710
0$
#711
b100011 8
1$
#712
0$
#713
b100100 8
1$
#714
0$
#715
b100101 8
1$
#716
0$
#717
b100110 8
1$
#718
0$
#719
b100111 8
1$
#720
0$
#721
b111 7
b0 8
1$
#722
0$
#723
b1 8
1$
#724
0$
#725
b10 8
1$
#726
0$
#727
b11 8
1$
#728
0$
#729
b100 8
1$
#730
0$
#731
b101 8
1$
#732
0$
#733
b110 8
1$
#734
0$
#735
b111 8
1$
#736
0$
#737
b1000 8
1$
#738
0$
#739
b1001 8
1$
#740
0$
#741
b1010 8
1$
#742
0$
#743
b1011 8
1$
#744
0$
#745
b1100 8
1$
#746
0$
#747
b1101 8
1$
#748
0$
#749
b1110 8
1$
#750
0$
#751
b1111 8
1$
#752
0$
#753
b10000 8
1$
#754
0$
#755
b10001 8
1$
#756
0$
#757
b10010 8
1$
#758
0$
#759
b10011 8
1$
#760
0$
#761
b10100 8
1$
#762
0$
#763
b10101 8
1$
#764
0$
#765
b10110 8
1$
#766
0$
#767
b10111 8
1$
#768
0$
#769
b11000 8
1$
#770
0$
#771
b11001 8
1$
#772
0$
#773
b11010 8
1$
#774
0$
#775
b11011 8
1$
#776
0$
#777
b11100 8
1$
#778
0$
#779
b11101 8
1$
#780
0$
#781
b11110 8
1$
#782
0$
#783
b11111 8
1$
#784
0$
#785
b100000 8
1$
#786
0$
#787
b100001 8
1$
#788
0$
#789
b100010 8
1$
#790
0$
#791
b100011 8
1$
#792
0$
#793
b100100 8
1$
#794
0$
#795
b100101 8
1$
#796
0$
#797
b100110 8
1$
#798
0$
#799
b100111 8
1$
#800
0$
#801
b1000 7
b0 8
b10101010 :
1$
#802
0$
#803
b1 8
1$
#804
0$
#805
b10 8
1$
#806
0$
#807
b11 8
1$
#808
0$
#809
b100 8
1$
#810
0$
#811
b101 8
1$
#812
0$
#813
b110 8
1$
#814
0$
#815
b111 8
1$
#816
0$
#817
b1000 8
1$
#818
0$
#819
b1001 8
1$
#820
0$
#821
b1010 8
1$
#822
0$
#823
b1011 8
1$
#824
0$
#825
b1100 8
1$
#826
0$
#827
b1101 8
1$
#828
0$
#829
b1110 8
1$
#830
0$
#831
b1111 8
1$
#832
0$
#833
b10000 8
1$
#834
0$
#835
b10001 8
1$
#836
0$
#837
b10010 8
1$
#838
0$
#839
b10011 8
1$
#840
0$
#841
b10100 8
1$
#842
0$
#843
b10101 8
1$
#844
0$
#845
b10110 8
1$
#846
0$
#847
b10111 8
1$
#848
0$
#849
b11000 8
1$
#850
0$
#851
b11001 8
1$
#852
0$
#853
b11010 8
1$
#854
0$
#855
b11011 8
1$
#856
0$
#857
b11100 8
1$
#858
0$
#859
b11101 8
1$
#860
0$
#861
b11110 8
1$
#862
0$
#863
b11111 8
1$
#864
0$
#865
b100000 8
1$
#866
0$
#867
b100001 8
1$
#868
0$
#869
b100010 8
1$
#870
0$
#871
b100011 8
1$
#872
0$
#873
b100100 8
1$
#874
0$
#875
b100101 8
1$
#876
0$
#877
b100110 8
1$
#878
0$
#879
b100111 8
1$
#880
0$
#881
b1001 7
b0 8
1$
#882
0$
#883
b1 8
1$
#884
0$
#885
b10 8
1$
#886
0$
#887
b11 8
1$
#888
0$
#889
b100 8
1$
#890
0$
#891
b101 8
1$
#892
0$
#893
b110 8
1$
#894
0$
#895
b111 8
1$
#896
0$
#897
b1000 8
1$
#898
0$
#899
b1001 8
1$
#900
0$
#901
b1010 8
1$
#902
0$
#903
b1011 8
1$
#904
0$
#905
b1100 8
1$
#906
0$
#907
b1101 8
1$
#908
0$
#909
b1110 8
1$
#910
0$
#911
b1111 8
1$
#912
0$
#913
b10000 8
1$
#914
0$
#915
b10001 8
1$
#916
0$
#917
b10010 8
1$
#918
0$
#919
b10011 8
1$
#920
0$
#921
b10100 8
1$
#922
0$
#923
b10101 8
1$
#924
0$
#925
b10110 8
1$
#926
0$
#927
b10111 8
1$
#928
0$
#929
b11000 8
1$
#930
0$
#931
b11001 8
1$
#932
0$
#933
b11010 8
1$
#934
0$
#935
b11011 8
1$
#936
0$
#937
b11100 8
1$
#938
0$
#939
b11101 8
1$
#940
0$
#941
b11110 8
1$
#942
0$
#943
b11111 8
1$
#944
0$
#945
b100000 8
1$
#946
0$
#947
b100001 8
1$
#948
0$
#949
b100010 8
1$
#950
0$
#951
b100011 8
1$
#952
0$
#953
b100100 8
1$
#954
0$
#955
b100101 8
1$
#956
0$
#957
b100110 8
1$
#958
0$
#959
b100111 8
1$
#960
0$
b10 '
#961
b10 9
b0 7
b0 8
b1010101010 :
1$
#962
0$
#963
b1 8
1$
#964
0$
#965
b10 8
1$
#966
0$
#967
b11 8
1$
#968
0$
#969
b100 8
1$
#970
0$
#971
b101 8
1$
#972
0$
#973
b110 8
1$
#974
0$
#975
b111 8
1$
#976
0$
#977
b1000 8
1$
#978
0$
#979
b1001 8
1$
#980
0$
#981
b1010 8
1$
#982
0$
#983
b1011 8
1$
#984
0$
#985
b1100 8
1$
#986
0$
#987
b1101 8
1$
#988
0$
#989
b1110 8
1$
#990
0$
#991
b1111 8
1$
#992
0$
#993
b10000 8
1$
#994
0$
#995
b10001 8
1$
#996
0$
#997
b10010 8
1$
#998
0$
#999
b10011 8
1$
#1000
0$
#1001
b10100 8
1$
#1002
0$
#1003
b10101 8
1$
#1004
0$
#1005
b10110 8
1$
#1006
0$
#1007
b10111 8
1$
#1008
0$
#1009
b11000 8
1$
#1010
0$
#1011
b11001 8
1$
#1012
0$
#1013
b11010 8
1$
#1014
0$
#1015
b11011 8
1$
#1016
0$
#1017
b11100 8
1$
#1018
0$
#1019
b11101 8
1$
#1020
0$
#1021
b11110 8
1$
#1022
0$
#1023
b11111 8
1$
#1024
0$
#1025
b100000 8
1$
#1026
0$
#1027
b100001 8
1$
#1028
0$
#1029
b100010 8
1$
#1030
0$
#1031
b100011 8
1$
#1032
0$
#1033
b100100 8
1$
#1034
0$
#1035
b100101 8
1$
#1036
0$
#1037
b100110 8
1$
#1038
0$
#1039
b100111 8
1$
#1040
0$
#1041
b1 7
0!
b0 8
1$
#1042
0$
#1043
b1 8
1$
#1044
0$
#1045
b10 8
1$
#1046
0$
#1047
b11 8
1$
#1048
0$
#1049
b100 8
1$
#1050
0$
#1051
b101 8
1$
#1052
0$
#1053
b110 8
1$
#1054
0$
#1055
b111 8
1$
#1056
0$
#1057
b1000 8
1$
#1058
0$
#1059
b1001 8
1$
#1060
0$
#1061
b1010 8
1$
#1062
0$
#1063
b1011 8
1$
#1064
0$
#1065
b1100 8
1$
#1066
0$
#1067
b1101 8
1$
#1068
0$
#1069
b1110 8
1$
#1070
0$
#1071
b1111 8
1$
#1072
0$
#1073
b10000 8
1$
#1074
0$
#1075
b10001 8
1$
#1076
0$
#1077
b10010 8
1$
#1078
0$
#1079
b10011 8
1$
#1080
0$
#1081
b10100 8
1$
#1082
0$
#1083
b10101 8
1$
#1084
0$
#1085
b10110 8
1$
#1086
0$
#1087
b10111 8
1$
#1088
0$
#1089
b11000 8
1$
#1090
0$
#1091
b11001 8
1$
#1092
0$
#1093
b11010 8
1$
#1094
0$
#1095
b11011 8
1$
#1096
0$
#1097
b11100 8
1$
#1098
0$
#1099
b11101 8
1$
#1100
0$
#1101
b11110 8
1$
#1102
0$
#1103
b11111 8
1$
#1104
0$
#1105
b100000 8
1$
#1106
0$
#1107
b100001 8
1$
#1108
0$
#1109
b100010 8
1$
#1110
0$
#1111
b100011 8
1$
#1112
0$
#1113
b100100 8
1$
#1114
0$
#1115
b100101 8
1$
#1116
0$
#1117
b100110 8
1$
#1118
0$
#1119
b100111 8
1$
#1120
0$
#1121
b10 7
1!
b0 8
1$
#1122
0$
#1123
b1 8
1$
#1124
0$
#1125
b10 8
1$
#1126
0$
#1127
b11 8
1$
#1128
0$
#1129
b100 8
1$
#1130
0$
#1131
b101 8
1$
#1132
0$
#1133
b110 8
1$
#1134
0$
#1135
b111 8
1$
#1136
0$
#1137
b1000 8
1$
#1138
0$
#1139
b1001 8
1$
#1140
0$
#1141
b1010 8
1$
#1142
0$
#1143
b1011 8
1$
#1144
0$
#1145
b1100 8
1$
#1146
0$
#1147
b1101 8
1$
#1148
0$
#1149
b1110 8
1$
#1150
0$
#1151
b1111 8
1$
#1152
0$
#1153
b10000 8
1$
#1154
0$
#1155
b10001 8
1$
#1156
0$
#1157
b10010 8
1$
#1158
0$
#1159
b10011 8
1$
#1160
0$
#1161
b10100 8
1$
#1162
0$
#1163
b10101 8
1$
#1164
0$
#1165
b10110 8
1$
#1166
0$
#1167
b10111 8
1$
#1168
0$
#1169
b11000 8
1$
#1170
0$
#1171
b11001 8
1$
#1172
0$
#1173
b11010 8
1$
#1174
0$
#1175
b11011 8
1$
#1176
0$
#1177
b11100 8
1$
#1178
0$
#1179
b11101 8
1$
#1180
0$
#1181
b11110 8
1$
#1182
0$
#1183
b11111 8
1$
#1184
0$
#1185
b100000 8
1$
#1186
0$
#1187
b100001 8
1$
#1188
0$
#1189
b100010 8
1$
#1190
0$
#1191
b100011 8
1$
#1192
0$
#1193
b100100 8
1$
#1194
0$
#1195
b100101 8
1$
#1196
0$
#1197
b100110 8
1$
#1198
0$
#1199
b100111 8
1$
#1200
0$
#1201
b11 7
0!
b0 8
1$
#1202
0$
#1203
b1 8
1$
#1204
0$
#1205
b10 8
1$
#1206
0$
#1207
b11 8
1$
#1208
0$
#1209
b100 8
1$
#1210
0$
#1211
b101 8
1$
#1212
0$
#1213
b110 8
1$
#1214
0$
#1215
b111 8
1$
#1216
0$
#1217
b1000 8
1$
#1218
0$
#1219
b1001 8
1$
#1220
0$
#1221
b1010 8
1$
#1222
0$
#1223
b1011 8
1$
#1224
0$
#1225
b1100 8
1$
#1226
0$
#1227
b1101 8
1$
#1228
0$
#1229
b1110 8
1$
#1230
0$
#1231
b1111 8
1$
#1232
0$
#1233
b10000 8
1$
#1234
0$
#1235
b10001 8
1$
#1236
0$
#1237
b10010 8
1$
#1238
0$
#1239
b10011 8
1$
#1240
0$
#1241
b10100 8
1$
#1242
0$
#1243
b10101 8
1$
#1244
0$
#1245
b10110 8
1$
#1246
0$
#1247
b10111 8
1$
#1248
0$
#1249
b11000 8
1$
#1250
0$
#1251
b11001 8
1$
#1252
0$
#1253
b11010 8
1$
#1254
0$
#1255
b11011 8
1$
#1256
0$
#1257
b11100 8
1$
#1258
0$
#1259
b11101 8
1$
#1260
0$
#1261
b11110 8
1$
#1262
0$
#1263
b11111 8
1$
#1264
0$
#1265
b100000 8
1$
#1266
0$
#1267
b100001 8
1$
#1268
0$
#1269
b100010 8
1$
#1270
0$
#1271
b100011 8
1$
#1272
0$
#1273
b100100 8
1$
#1274
0$
#1275
b100101 8
1$
#1276
0$
#1277
b100110 8
1$
#1278
0$
#1279
b100111 8
1$
#1280
0$
#1281
b100 7
1!
b0 8
1$
#1282
0$
#1283
b1 8
1$
#1284
0$
#1285
b10 8
1$
#1286
0$
#1287
b11 8
1$
#1288
0$
#1289
b100 8
1$
#1290
0$
#1291
b101 8
1$
#1292
0$
#1293
b110 8
1$
#1294
0$
#1295
b111 8
1$
#1296
0$
#1297
b1000 8
1$
#1298
0$
#1299
b1001 8
1$
#1300
0$
#1301
b1010 8
1$
#1302
0$
#1303
b1011 8
1$
#1304
0$
#1305
b1100 8
1$
#1306
0$
#1307
b1101 8
1$
#1308
0$
#1309
b1110 8
1$
#1310
0$
#1311
b1111 8
1$
#1312
0$
#1313
b10000 8
1$
#1314
0$
