s2/UART2/UART.v
module UART (
    input rx,
    input clk,
    output reg [7:0] data_bus
);

reg [7:0] the_byte = 8'b00000000; 
reg [2:0] byte_index = 3'b000;
reg [2:0] reciever_state = 3'b000;

// imutable variables (possible states)
parameter idle = 3'b000; // listening
parameter start_bit = 3'b001; // reading
parameter reading_bits = 3'b010;
parameter stop_bit = 3'b100;


// Okay now I have the basic functionality of the UART
// Now comes the hard part.  I nee to implement the baud rate.
// basically I should be reading the bits in the middle of their
// signal.  


always @(posedge clk) begin
    case (reciever_state)
    idle:
    begin
        if (rx == 1'b1)
            reciever_state <= idle;
        else
            reciever_state <= start_bit;
    end
    start_bit:
    begin
        if (rx == 1'b0) // active low uart
            reciever_state <= reading_bits;
        else
            reciever_state <= idle;
    end
    reading_bits:
    begin
        if (byte_index < 7) begin
            the_byte[byte_index] <= rx;
            byte_index <= byte_index + 1;
            reciever_state <= reading_bits;
        end
        else begin
            byte_index <= 3'b000;
            reciever_state <= stop_bit;
        end
    end
    stop_bit:
    begin 
        data_bus <= the_byte;
        reciever_state <= idle;
    end
    endcase
end
endmodule

s2/UART2/UART_tb.v
`timescale 1ns / 1ns;
module UART_tb;

reg  rx;
reg clk;
wire [7:0] data_bus;


UART    u0 (
        .rx (rx),
        .clk (clk),
        .data_bus (data_bus)
);

initial begin
    $dumpfile("uart_dump.vcd");
    $dumpvars(0, UART_tb);
    // sim the transmission

    clk <= 0;
    rx <= 1; // idle
    #80 rx <= 0; // start bit
    #80 rx <= 0;
    #80 rx <= 1;
    #80 rx <= 0;
    #80 rx <= 1;
    #80 rx <= 0;
    #80 rx <= 1;
    #80 rx <= 0;
    #80 rx <= 1;
    #80 rx <= 1;

    #100;
    $display("Final data_bus value: %b", data_bus);
    $finish;
end

always #1 clk = ~clk;

endmodule

s2/UART2/uart_dump.vcd
$date
	Thu Aug 15 12:34:43 2024
$end
$version
	Icarus Verilog
$end
$timescale
	1ns
$end
$scope module UART_tb $end
$var wire 8 ! data_bus [7:0] $end
$var reg 1 " clk $end
$var reg 1 # rx $end
$scope module u0 $end
$var wire 1 " clk $end
$var wire 1 # rx $end
$var parameter 3 $ idle $end
$var parameter 3 % reading_bits $end
$var parameter 3 & start_bit $end
$var parameter 3 ' stop_bit $end
$var reg 3 ( byte_index [2:0] $end
$var reg 8 ) data_bus [7:0] $end
$var reg 3 * reciever_state [2:0] $end
$var reg 8 + the_byte [7:0] $end
$upscope $end
$upscope $end
$enddefinitions $end
$comment Show the parameter values. $end
$dumpall
b100 '
b1 &
b10 %
b0 $
$end
#0
$dumpvars
b0 +
b0 *
bx )
b0 (
1#
0"
bx !
$end
#1
1"
#2
0"
#3
1"
#4
0"
#5
1"
#6
0"
#7
1"
#8
0"
#9
1"
#10
0"
#11
1"
#12
0"
#13
1"
#14
0"
#15
1"
#16
0"
#17
1"
#18
0"
#19
1"
#20
0"
#21
1"
#22
0"
#23
1"
#24
0"
#25
1"
#26
0"
#27
1"
#28
0"
#29
1"
#30
0"
#31
1"
#32
0"
#33
1"
#34
0"
#35
1"
#36
0"
#37
1"
#38
0"
#39
1"
#40
0"
#41
1"
#42
0"
#43
1"
#44
0"
#45
1"
#46
0"
#47
1"
#48
0"
#49
1"
#50
0"
#51
1"
#52
0"
#53
1"
#54
0"
#55
1"
#56
0"
#57
1"
#58
0"
#59
1"
#60
0"
#61
1"
#62
0"
#63
1"
#64
0"
#65
1"
#66
0"
#67
1"
#68
0"
#69
1"
#70
0"
#71
1"
#72
0"
#73
1"
#74
0"
#75
1"
#76
0"
#77
1"
#78
0"
#79
1"
#80
0#
0"
#81
b1 *
1"
#82
0"
#83
b10 *
1"
#84
0"
#85
b1 (
1"
#86
0"
#87
b10 (
1"
#88
0"
#89
b11 (
1"
#90
0"
#91
b100 (
1"
#92
0"
#93
b101 (
1"
#94
0"
#95
b110 (
1"
#96
0"
#97
b111 (
1"
#98
0"
#99
b100 *
b0 (
1"
#100
0"
#101
b0 *
b0 !
b0 )
1"
#102
0"
#103
b1 *
1"
#104
0"
#105
b10 *
1"
#106
0"
#107
b1 (
1"
#108
0"
#109
b10 (
1"
#110
0"
#111
b11 (
1"
#112
0"
#113
b100 (
1"
#114
0"
#115
b101 (
1"
#116
0"
#117
b110 (
1"
#118
0"
#119
b111 (
1"
#120
0"
#121
b100 *
b0 (
1"
#122
0"
#123
b0 *
1"
#124
0"
#125
b1 *
1"
#126
0"
#127
b10 *
1"
#128
0"
#129
b1 (
1"
#130
0"
#131
b10 (
1"
#132
0"
#133
b11 (
1"
#134
0"
#135
b100 (
1"
#136
0"
#137
b101 (
1"
#138
0"
#139
b110 (
1"
#140
0"
#141
b111 (
1"
#142
0"
#143
b100 *
b0 (
1"
#144
0"
#145
b0 *
1"
#146
0"
#147
b1 *
1"
#148
0"
#149
b10 *
1"
#150
0"
#151
b1 (
1"
#152
0"
#153
b10 (
1"
#154
0"
#155
b11 (
1"
#156
0"
#157
b100 (
1"
#158
0"
#159
b101 (
1"
#160
0"
#161
b110 (
1"
#162
0"
#163
b111 (
1"
#164
0"
#165
b100 *
b0 (
1"
#166
0"
#167
b0 *
1"
#168
0"
#169
b1 *
1"
#170
0"
#171
b10 *
1"
#172
0"
#173
b1 (
1"
#174
0"
#175
b10 (
1"
#176
0"
#177
b11 (
1"
#178
0"
#179
b100 (
1"
#180
0"
#181
b101 (
1"
#182
0"
#183
b110 (
1"
#184
0"
#185
b111 (
1"
#186
0"
#187
b100 *
b0 (
1"
#188
0"
#189
b0 *
1"
#190
0"
#191
b1 *
1"
#192
0"
#193
b10 *
1"
#194
0"
#195
b1 (
1"
#196
0"
#197
b10 (
1"
#198
0"
#199
b11 (
1"
#200
0"
#201
b100 (
1"
#202
0"
#203
b101 (
1"
#204
0"
#205
b110 (
1"
#206
0"
#207
b111 (
1"
#208
0"
#209
b100 *
b0 (
1"
#210
0"
#211
b0 *
1"
#212
0"
#213
b1 *
1"
#214
0"
#215
b10 *
1"
#216
0"
#217
b1 (
1"
#218
0"
#219
b10 (
1"
#220
0"
#221
b11 (
1"
#222
0"
#223
b100 (
1"
#224
0"
#225
b101 (
1"
#226
0"
#227
b110 (
1"
#228
0"
#229
b111 (
1"
#230
0"
#231
b100 *
b0 (
1"
#232
0"
#233
b0 *
1"
#234
0"
#235
b1 *
1"
#236
0"
#237
b10 *
1"
#238
0"
#239
b1 (
1"
#240
1#
0"
#241
b10 (
b10 +
1"
#242
0"
#243
b11 (
b110 +
1"
#244
0"
#245
b100 (
b1110 +
1"
#246
0"
#247
b101 (
b11110 +
1"
#248
0"
#249
b110 (
b111110 +
1"
#250
0"
#251
b111 (
b1111110 +
1"
#252
0"
#253
b100 *
b0 (
1"
#254
0"
#255
b0 *
b1111110 !
b1111110 )
1"
